consul_ha
