Metadata-Version: 1.1
Name: consul-ha
Version: 0.1.38
Summary: Server for managing application state and high availability using Consul
Home-page: https://github.com/mongohq/consul_ha
Author: Chris Winslett
Author-email: chris@compose.io
License: MIT
Keywords: consul high availablity
Platform: UNKNOWN
Classifier: Development Status :: 3 - Alpha
Classifier: Intended Audience :: Developers
Classifier: Topic :: Software Development :: Build Tools
Classifier: License :: OSI Approved :: MIT License
Classifier: Programming Language :: Python :: 2.7
